MANIFEST.in
setup.py
ghostia/__init__.py
ghostia/asgi.py
ghostia/client.py
ghostia/utils.py
ghostia.egg-info/PKG-INFO
ghostia.egg-info/SOURCES.txt
ghostia.egg-info/dependency_links.txt
ghostia.egg-info/entry_points.txt
ghostia.egg-info/top_level.txt
ghostia/bin/ghostia
ghostia/server/__init__.py
ghostia/server/channeler.py
ghostia/server/config.py
ghostia/server/decorators.py
ghostia/server/exceptions.py
ghostia/server/generators.py
ghostia/server/globals.py
ghostia/server/initialization.py
ghostia/server/memory.py
ghostia/server/types.py