Metadata-Version: 1.0
Name: ghostia
Version: 0.0.1
Summary: Plataforma de creacion de agentes inteligentes artificiales generales
Home-page: https://zerpatechnology.com/projects/ghostia
Author: Jesus Zerpa
Author-email: support@zerpatechnology.com
License: UNKNOWN
Keywords: IA
Platform: UNKNOWN
